aind_zarr_utils/__init__.py
aind_zarr_utils/annotations.py
aind_zarr_utils/neuroglancer.py
aind_zarr_utils/pipeline_domain_selector.py
aind_zarr_utils/pipeline_transformed.py
aind_zarr_utils/py.typed
aind_zarr_utils/zarr.py
aind_zarr_utils-0.11.5.dist-info/licenses/LICENSE
aind_zarr_utils-0.11.5.dist-info/METADATA
aind_zarr_utils-0.11.5.dist-info/WHEEL
aind_zarr_utils-0.11.5.dist-info/top_level.txt
aind_zarr_utils-0.11.5.dist-info/RECORD
