Metadata-Version: 2.4
Name: aind-zarr-utils
Version: 0.11.5
Summary: Utilities for working with ZARR data and AIND metadata
Author: Allen Institute for Neural Dynamics
Author-email: Galen Lynch <galen@galenlynch.com>
License-Expression: MIT
Project-URL: Repository, https://github.com/AllenNeuralDynamics/aind-zarr-utils/
Project-URL: Issues, https://github.com/AllenNeuralDynamics/aind-zarr-utils/issues
Project-URL: Changelog, https://github.com/AllenNeuralDynamics/aind-zarr-utils/blob/main/CHANGELOG.md
Classifier: Programming Language :: Python :: 3
Requires-Python: >=3.10
License-File: LICENSE
Requires-Dist: aind-anatomical-utils<0.5,>=0.4
Requires-Dist: aind-registration-utils<0.5,>=0.1
Requires-Dist: aind-s3-cache<0.2,>=0.1
Requires-Dist: antspyx<0.7,>=0.2
Requires-Dist: numpy<3,>=2
Requires-Dist: ome-zarr<0.13,>=0.7
Requires-Dist: requests<3,>=2
Requires-Dist: s3fs[boto3]>=2021
Requires-Dist: SimpleITK<3,>=2
Dynamic: license-file
